 {
     "criteria": [{
             "kriteria": "Jumlah Gol",
             "bobot": 5,
             "jenis": "Benefit"
         },
         {
             "kriteria": "Jumlah Assist",
             "bobot": 4,
             "jenis": "Benefit"
         },
         {
             "kriteria": "Shot on Target",
             "bobot": 5,
             "jenis": "Benefit"
         },
         {
             "kriteria": "Kemenangan Tim",
             "bobot": 3,
             "jenis": "Benefit"
         },
         {
             "kriteria": "Waktu Bermain",
             "bobot": 3,
             "jenis": "Benefit"
         }
     ],
     "alternatif": [{
             "nama": "Silver Ash",
             "1": 15,
             "2": 20,
             "3": 18,
             "4": 11,
             "5": 321
         },
         {
             "nama": "Hellagur",
             "1": 12,
             "2": 17,
             "3": 14,
             "4": 17,
             "5": 311
         },
         {
             "nama": "Flamebringer",
             "1": 10,
             "2": 27,
             "3": 12,
             "4": 16,
             "5": 421
         },
         {
             "nama": "Courier",
             "1": 19,
             "2": 6,
             "3": 25,
             "4": 18,
             "5": 440
         },
         {
             "nama": "Matterhorn",
             "1": 15,
             "2": 19,
             "3": 29,
             "4": 12,
             "5": 329
         }
     ]
 }